sttable/__init__.py
sttable/parser.py
sttable/table.py
sttable-0.0.1.dist-info/LICENSE
sttable-0.0.1.dist-info/METADATA
sttable-0.0.1.dist-info/WHEEL
sttable-0.0.1.dist-info/top_level.txt
sttable-0.0.1.dist-info/RECORD
